setup.py
WintxImporter_Grib.egg-info/PKG-INFO
WintxImporter_Grib.egg-info/SOURCES.txt
WintxImporter_Grib.egg-info/dependency_links.txt
WintxImporter_Grib.egg-info/namespace_packages.txt
WintxImporter_Grib.egg-info/requires.txt
WintxImporter_Grib.egg-info/top_level.txt
test/test_wintx_grib_importer.py
wintx/__init__.py
wintx/importers/__init__.py
wintx/importers/Grib/Importer.py
wintx/importers/Grib/__init__.py